Metadata-Version: 1.0
Name: gg-dist
Version: 0.1
Summary: Gaussian and Binomial distributions
Home-page: UNKNOWN
Author: Goutam Kumar Ghadai
Author-email: goutam.ghadai2199@gmail.com
License: UNKNOWN
Platform: UNKNOWN
